django_superapp/__init__.py
django_superapp/apps.py
django_superapp/settings.py
django_superapp/urls.py
django_superapp/cli/__init__.py
django_superapp/cli/main.py
django_superapp/cli/utils.py
superapp-1.2.17.dist-info/LICENSE.md
superapp-1.2.17.dist-info/METADATA
superapp-1.2.17.dist-info/WHEEL
superapp-1.2.17.dist-info/entry_points.txt
superapp-1.2.17.dist-info/top_level.txt
superapp-1.2.17.dist-info/RECORD
